cli/__init__.py
cli/main.py
commands/__init__.py
commands/components.py
commands/logs.py
commands/nodes.py
commands/registries.py
commands/repositories.py
commands/servers.py
commands/shell.py
commands/stacks.py
core/__init__.py
core/api_client.py
core/cache_manager.py
core/completion.py
core/config.py
core/http_client.py
core/progress.py
core/security.py
core/services/__init__.py
core/services/base.py
core/services/components_service.py
core/services/nodes_service.py
core/services/registries_service.py
core/services/repositories_service.py
core/services/servers_service.py
core/services/stacks_service.py
imgctl-3.0.15.dist-info/licenses/LICENSE
imgctl-3.0.15.dist-info/licenses/LICENSE-COMMERCIAL
utils/__init__.py
utils/column_utils.py
utils/dynamic_columns.py
utils/formatters.py
utils/highlighter.py
utils/validators.py
utils/verbose.py
imgctl-3.0.15.dist-info/METADATA
imgctl-3.0.15.dist-info/WHEEL
imgctl-3.0.15.dist-info/entry_points.txt
imgctl-3.0.15.dist-info/top_level.txt
imgctl-3.0.15.dist-info/RECORD
