Metadata-Version: 2.4
Name: imgctl
Version: 3.0.15
Summary: Консольная утилита для управления контейнерной платформой Imagenarium
Author: @koden8
Maintainer: @koden8
License: MIT License (non-commercial) / Commercial License
Project-URL: Homepage, https://gitlab.com/koden8/imgctl
Project-URL: Documentation, https://gitlab.com/koden8/imgctl#readme
Project-URL: Repository, https://gitlab.com/koden8/imgctl
Project-URL: Issues, https://gitlab.com/koden8/imgctl/-/issues
Project-URL: Changelog, https://gitlab.com/koden8/imgctl/-/blob/main/CHANGELOG.md
Keywords: docker,containers,orchestration,cli,imagenarium
Classifier: Development Status :: 5 - Production/Stable
Classifier: Intended Audience :: Developers
Classifier: Intended Audience :: System Administrators
Classifier: License :: OSI Approved :: MIT License
Classifier: Operating System :: OS Independent
Classifier: Programming Language :: Python :: 3
Classifier: Programming Language :: Python :: 3.8
Classifier: Programming Language :: Python :: 3.9
Classifier: Programming Language :: Python :: 3.10
Classifier: Programming Language :: Python :: 3.11
Classifier: Programming Language :: Python :: 3.12
Classifier: Topic :: Software Development :: Libraries :: Python Modules
Classifier: Topic :: System :: Systems Administration
Classifier: Topic :: Utilities
Requires-Python: >=3.8
License-File: LICENSE
License-File: LICENSE-COMMERCIAL
Requires-Dist: click>=8.0.0
Requires-Dist: requests>=2.25.0
Requires-Dist: pyyaml>=6.0
Requires-Dist: tabulate>=0.9.0
Requires-Dist: colorama>=0.4.4
Requires-Dist: rich>=12.0.0
Requires-Dist: textual>=0.41.0
Requires-Dist: keyring>=23.0.0
Requires-Dist: keyrings.alt>=5.0.0
Requires-Dist: prompt-toolkit>=3.0.0
Provides-Extra: dev
Requires-Dist: pytest>=6.0; extra == "dev"
Requires-Dist: pytest-cov>=2.0; extra == "dev"
Requires-Dist: black>=21.0; extra == "dev"
Requires-Dist: flake8>=3.8; extra == "dev"
Requires-Dist: mypy>=0.800; extra == "dev"
Dynamic: license-file
